{
	"name": "df_cast_dateformat",
	"properties": {
		"type": "MappingDataFlow",
		"typeProperties": {
			"sources": [
				{
					"dataset": {
						"referenceName": "Parquet_bronze",
						"type": "DatasetReference"
					},
					"name": "source1"
				}
			],
			"sinks": [
				{
					"dataset": {
						"referenceName": "Parquet_gold",
						"type": "DatasetReference"
					},
					"name": "sink1"
				}
			],
			"transformations": [
				{
					"name": "derivedColumn1"
				}
			],
			"scriptLines": [
				"source(output(",
				"          AddressID as integer,",
				"          AddressLine1 as string,",
				"          AddressLine2 as string,",
				"          City as string,",
				"          StateProvince as string,",
				"          CountryRegion as string,",
				"          PostalCode as string,",
				"          rowguid as string,",
				"          ModifiedDate as timestamp",
				"     ),",
				"     allowSchemaDrift: true,",
				"     validateSchema: false,",
				"     ignoreNoFilesFound: false,",
				"     format: 'parquet') ~> source1",
				"source1 derive(ModifiedDate = toDate(ModifiedDate)) ~> derivedColumn1",
				"derivedColumn1 sink(allowSchemaDrift: true,",
				"     validateSchema: false,",
				"     format: 'parquet',",
				"     umask: 0022,",
				"     preCommands: [],",
				"     postCommands: [],",
				"     skipDuplicateMapInputs: true,",
				"     skipDuplicateMapOutputs: true,",
				"     mapColumn(",
				"          Address_ID = AddressID,",
				"          Address_Line1 = AddressLine1,",
				"          Address_Line2 = AddressLine2,",
				"          City,",
				"          State_Province = StateProvince,",
				"          Country_Region = CountryRegion,",
				"          Postal_Code = PostalCode,",
				"          rowguid,",
				"          Modified_Date = ModifiedDate",
				"     )) ~> sink1"
			]
		}
	}
}